archie/__init__.py
archie/cli.py
archie/disk.py
archie/env.py
archie/task.py
archie_cli-0.6.9.dist-info/METADATA
archie_cli-0.6.9.dist-info/WHEEL
archie_cli-0.6.9.dist-info/entry_points.txt
archie_cli-0.6.9.dist-info/licenses/LICENSE
archie_cli-0.6.9.dist-info/RECORD
