Metadata-Version: 2.4
Name: archie-cli
Version: 0.6.9
Summary: A command line tool to make managing your Linux system easier
License-File: LICENSE
Author: Helix128
Requires-Python: >=3.11
Classifier: Development Status :: 4 - Beta
Classifier: Intended Audience :: End Users/Desktop
Classifier: Programming Language :: Python :: 3
Classifier: Operating System :: POSIX :: Linux
Requires-Dist: click (>=8.3.0,<9.0.0)
Requires-Dist: platformdirs (>=4.4.0,<5.0.0)
Project-URL: Homepage, https://github.com/helix128/archie
